docker_shaper/__init__.py
docker_shaper/docker_state.py
docker_shaper/dynamic.py
docker_shaper/headless_examples/docker_events.py
docker_shaper/headless_examples/docker_prune.py
docker_shaper/headless_examples/dockermon.py
docker_shaper/server.py
docker_shaper/utils.py
docker_shaper/version.py
docker_shaper-2.1.0.dist-info/METADATA
docker_shaper-2.1.0.dist-info/WHEEL
docker_shaper-2.1.0.dist-info/entry_points.txt
docker_shaper-2.1.0.dist-info/RECORD
