Metadata-Version: 2.1
Name: docker-shaper
Version: 2.1.0
Summary: Keeps Docker resources in shape based on rules and usage
Author: Frans Fürst
Author-email: frans.fuerst@checkmk.com
Requires-Python: >=3.10.4,<4.0.0
Classifier: Programming Language :: Python :: 3
Classifier: Programming Language :: Python :: 3.11
Classifier: Programming Language :: Python :: 3.12
Classifier: Programming Language :: Python :: 3.13
Requires-Dist: aiodocker (>=0,<1)
Requires-Dist: apparat (>=0.0.8,<0.0.9)
Requires-Dist: psutil (>=5.9.8,<6.0.0)
Requires-Dist: pydantic (>=2.4,<3.0)
Requires-Dist: pytz (>=2023.3.post1,<2024.0)
Requires-Dist: rich (>=13,<14)
Requires-Dist: textual (>=0,<1)
Requires-Dist: trickkiste (>=0.2.1,<0.3.0)
